{
  "sports": {
    "emoji": "\u26bd",
    "headlines": [
      {
        "headline": "Tennis Pro Makes Historic Comeback After Injury",
        "text": "After a career-threatening injury, a tennis professional has made an incredible comeback, winning their first major tournament since returning to competition.",
        "sources": [
          "Reuters",
          "CNN",
          "Associated Press"
        ]
      },
      {
        "headline": "Major League Baseball Opening Day Breaks Attendance Records",
        "text": "A rising soccer star has broken the single-season goal-scoring record in one of Europe's top leagues, cementing their place in the sport's history.",
        "sources": [
          "The New York Times"
        ]
      },
      {
        "headline": "Soccer Star Sets New Goal-Scoring Record in European League",
        "text": "The International Olympic Committee has selected a new host city for the 2032 Summer Games, marking a significant milestone in Olympic history.",
        "sources": [
          "NPR"
        ]
      }
    ]
  },
  "technology": {
    "emoji": "\ud83d\udcbb",
    "headlines": [
      {
        "headline": "Tech Giant Unveils Revolutionary Quantum Computing Breakthrough",
        "text": "The latest software update from a major tech company includes significant security enhancements and new features designed to protect user data.",
        "sources": [
          "CNN"
        ]
      },
      {
        "headline": "New AI Model Breaks Performance Records in Language Tasks",
        "text": "The latest software update from a major tech company includes significant security enhancements and new features designed to protect user data.",
        "sources": [
          "The Guardian"
        ]
      },
      {
        "headline": "Startup Develops Breakthrough in Battery Technology",
        "text": "The latest software update from a major tech company includes significant security enhancements and new features designed to protect user data.",
        "sources": [
          "Bloomberg",
          "The Washington Post"
        ]
      }
    ]
  },
  "business": {
    "emoji": "\ud83d\udcbc",
    "headlines": [
      {
        "headline": "Major Merger Creates New Industry Leader",
        "text": "A major retail chain has announced plans to open hundreds of new locations nationwide, creating thousands of new jobs in the process.",
        "sources": [
          "NPR",
          "Associated Press"
        ]
      },
      {
        "headline": "Startup Secures Record-Breaking Funding Round",
        "text": "Global financial markets have reached new record highs, driven by strong economic indicators and positive corporate earnings reports.",
        "sources": [
          "NPR",
          "The Wall Street Journal"
        ]
      },
      {
        "headline": "Global Markets Reach New All-Time High",
        "text": "Two major companies in the industry have announced a merger that will create the largest player in the sector, potentially reshaping the market landscape.",
        "sources": [
          "Bloomberg",
          "Reuters"
        ]
      }
    ]
  },
  "entertainment": {
    "emoji": "\ud83c\udfac",
    "headlines": [
      {
        "headline": "Streaming Service Announces Major Content Partnership",
        "text": "A leading streaming service has announced a major content partnership that will bring exclusive programming to its platform.",
        "sources": [
          "Associated Press",
          "CNN",
          "Bloomberg"
        ]
      },
      {
        "headline": "New TV Series Breaks Streaming Records",
        "text": "The annual award show celebrated its most-watched broadcast in history, with millions tuning in to see their favorite stars.",
        "sources": [
          "The Wall Street Journal",
          "NPR"
        ]
      },
      {
        "headline": "Music Festival Lineup Revealed, Features Major Headliners",
        "text": "The latest blockbuster movie has shattered box office records during its opening weekend, becoming the highest-grossing film of the year.",
        "sources": [
          "The Guardian",
          "The Wall Street Journal",
          "The New York Times"
        ]
      }
    ]
  },
  "science": {
    "emoji": "\ud83d\udd2c",
    "headlines": [
      {
        "headline": "Space Mission Returns with Unprecedented Data",
        "text": "Researchers have announced a major breakthrough in renewable energy storage technology that could revolutionize the clean energy sector.",
        "sources": [
          "Associated Press",
          "The Guardian"
        ]
      },
      {
        "headline": "Breakthrough in Renewable Energy Storage Announced",
        "text": "Scientists have discovered a new species during a deep-sea exploration mission, providing new insights into marine biodiversity.",
        "sources": [
          "CNN"
        ]
      },
      {
        "headline": "Climate Research Shows Promising New Solutions",
        "text": "Latest climate research has identified promising new solutions that could help mitigate the effects of global warming.",
        "sources": [
          "NPR",
          "CNN"
        ]
      }
    ]
  },
  "health": {
    "emoji": "\ud83c\udfe5",
    "headlines": [
      {
        "headline": "Breakthrough in Vaccine Development Announced",
        "text": "Clinical trials for a new medical treatment have shown promising results, potentially offering hope for patients with previously untreatable conditions.",
        "sources": [
          "NPR",
          "CNN"
        ]
      },
      {
        "headline": "New Medical Treatment Shows Promise in Clinical Trials",
        "text": "A mental health awareness campaign has reached millions of people, helping to reduce stigma and increase access to care.",
        "sources": [
          "NPR"
        ]
      },
      {
        "headline": "Public Health Initiative Reduces Disease Rates",
        "text": "A mental health awareness campaign has reached millions of people, helping to reduce stigma and increase access to care.",
        "sources": [
          "The New York Times",
          "The Washington Post"
        ]
      }
    ]
  },
  "politics": {
    "emoji": "\ud83c\udfdb\ufe0f",
    "headlines": [
      {
        "headline": "Diplomatic Breakthrough in International Relations",
        "text": "A diplomatic breakthrough has been achieved in international relations, easing tensions between major world powers.",
        "sources": [
          "The Guardian",
          "The Wall Street Journal",
          "CNN"
        ]
      },
      {
        "headline": "Major Policy Initiative Announced to Address Housing Crisis",
        "text": "The government has announced a major policy initiative to address the housing crisis, including new funding for affordable housing projects.",
        "sources": [
          "Associated Press"
        ]
      },
      {
        "headline": "Government Announces New Infrastructure Investment Plan",
        "text": "A new infrastructure investment plan has been unveiled, promising to modernize transportation systems and create thousands of jobs.",
        "sources": [
          "Associated Press",
          "The Wall Street Journal",
          "The New York Times"
        ]
      }
    ]
  },
  "gaming": {
    "emoji": "\ud83c\udfae",
    "headlines": [
      {
        "headline": "Gaming Platform Announces Cross-Platform Play Support",
        "text": "A popular gaming platform has announced support for cross-platform play, allowing players on different systems to compete and cooperate in the same games.",
        "sources": [
          "The New York Times",
          "CNN",
          "The Wall Street Journal"
        ]
      },
      {
        "headline": "Major Game Studio Announces Next-Gen Console Exclusive",
        "text": "A leading game studio has announced an exclusive title for next-generation consoles, featuring groundbreaking graphics and innovative gameplay mechanics.",
        "sources": [
          "Associated Press"
        ]
      },
      {
        "headline": "Virtual Reality Game Wins Multiple Industry Awards",
        "text": "The latest esports tournament has broken all previous viewership records, with millions of fans tuning in to watch the world's best players compete.",
        "sources": [
          "The Guardian",
          "CNN"
        ]
      }
    ]
  }
}