{
  "sports": {
    "emoji": "\u26bd",
    "headlines": [
      {
        "headline": "Major League Baseball Opening Day Breaks Attendance Records",
        "text": "The opening day of the MLB season saw record-breaking attendance across stadiums nationwide, with fans eager to return to live sports after the offseason.",
        "sources": [
          "NPR",
          "BBC News",
          "The New York Times"
        ]
      },
      {
        "headline": "NBA Playoff Race Heats Up in Final Regular Season Games",
        "text": "The opening day of the MLB season saw record-breaking attendance across stadiums nationwide, with fans eager to return to live sports after the offseason.",
        "sources": [
          "The Washington Post",
          "The Guardian"
        ]
      },
      {
        "headline": "Olympic Committee Announces New Host City for 2032 Games",
        "text": "With just a few games remaining in the regular season, several teams are battling for the final playoff spots in what has been one of the most competitive seasons in recent memory.",
        "sources": [
          "Reuters",
          "Bloomberg",
          "The Guardian"
        ]
      }
    ]
  },
  "technology": {
    "emoji": "\ud83d\udcbb",
    "headlines": [
      {
        "headline": "New AI Model Breaks Performance Records in Language Tasks",
        "text": "A new artificial intelligence model has achieved unprecedented performance in natural language processing tasks, potentially revolutionizing how we interact with technology.",
        "sources": [
          "Associated Press",
          "CNN",
          "The Washington Post"
        ]
      },
      {
        "headline": "Startup Develops Breakthrough in Battery Technology",
        "text": "A new artificial intelligence model has achieved unprecedented performance in natural language processing tasks, potentially revolutionizing how we interact with technology.",
        "sources": [
          "Associated Press"
        ]
      },
      {
        "headline": "Major Software Update Brings Enhanced Security Features",
        "text": "A startup company has developed a revolutionary new battery technology that could dramatically increase the range of electric vehicles.",
        "sources": [
          "Bloomberg",
          "The Guardian",
          "The Wall Street Journal"
        ]
      }
    ]
  },
  "business": {
    "emoji": "\ud83d\udcbc",
    "headlines": [
      {
        "headline": "Major Retailer Announces Nationwide Expansion",
        "text": "Global financial markets have reached new record highs, driven by strong economic indicators and positive corporate earnings reports.",
        "sources": [
          "Bloomberg",
          "BBC News",
          "Reuters"
        ]
      },
      {
        "headline": "New Economic Report Shows Strong Growth Indicators",
        "text": "Two major companies in the industry have announced a merger that will create the largest player in the sector, potentially reshaping the market landscape.",
        "sources": [
          "CNN",
          "BBC News"
        ]
      },
      {
        "headline": "Startup Secures Record-Breaking Funding Round",
        "text": "Global financial markets have reached new record highs, driven by strong economic indicators and positive corporate earnings reports.",
        "sources": [
          "NPR",
          "The Guardian",
          "Associated Press"
        ]
      }
    ]
  },
  "entertainment": {
    "emoji": "\ud83c\udfac",
    "headlines": [
      {
        "headline": "Award Show Celebrates Record-Breaking Viewership",
        "text": "The lineup for this year's major music festival has been revealed, featuring some of the biggest names in the industry as headliners.",
        "sources": [
          "The Washington Post"
        ]
      },
      {
        "headline": "Music Festival Lineup Revealed, Features Major Headliners",
        "text": "A leading streaming service has announced a major content partnership that will bring exclusive programming to its platform.",
        "sources": [
          "CNN",
          "Associated Press"
        ]
      },
      {
        "headline": "New TV Series Breaks Streaming Records",
        "text": "The latest blockbuster movie has shattered box office records during its opening weekend, becoming the highest-grossing film of the year.",
        "sources": [
          "The Guardian",
          "The Washington Post"
        ]
      }
    ]
  },
  "science": {
    "emoji": "\ud83d\udd2c",
    "headlines": [
      {
        "headline": "Researchers Discover New Species in Deep Ocean Exploration",
        "text": "Researchers have announced a major breakthrough in renewable energy storage technology that could revolutionize the clean energy sector.",
        "sources": [
          "The New York Times",
          "The Washington Post",
          "The Guardian"
        ]
      },
      {
        "headline": "Climate Research Shows Promising New Solutions",
        "text": "A new study has revealed groundbreaking insights into how the human brain processes information and forms memories.",
        "sources": [
          "Bloomberg",
          "CNN"
        ]
      },
      {
        "headline": "New Study Reveals Insights into Human Brain Function",
        "text": "Latest climate research has identified promising new solutions that could help mitigate the effects of global warming.",
        "sources": [
          "Reuters"
        ]
      }
    ]
  },
  "health": {
    "emoji": "\ud83c\udfe5",
    "headlines": [
      {
        "headline": "Mental Health Awareness Campaign Reaches Millions",
        "text": "Scientists have announced a breakthrough in vaccine development that could protect against multiple strains of a dangerous virus.",
        "sources": [
          "Bloomberg",
          "The Wall Street Journal"
        ]
      },
      {
        "headline": "Breakthrough in Vaccine Development Announced",
        "text": "A comprehensive new study has revealed significant benefits of regular exercise on longevity and overall health.",
        "sources": [
          "Bloomberg"
        ]
      },
      {
        "headline": "New Study Reveals Benefits of Exercise on Longevity",
        "text": "A mental health awareness campaign has reached millions of people, helping to reduce stigma and increase access to care.",
        "sources": [
          "The Wall Street Journal",
          "Bloomberg",
          "NPR"
        ]
      }
    ]
  },
  "politics": {
    "emoji": "\ud83c\udfdb\ufe0f",
    "headlines": [
      {
        "headline": "Diplomatic Breakthrough in International Relations",
        "text": "New legislation has been introduced that aims to reform the healthcare system, potentially expanding access to millions of citizens.",
        "sources": [
          "CNN"
        ]
      },
      {
        "headline": "Government Announces New Infrastructure Investment Plan",
        "text": "A new infrastructure investment plan has been unveiled, promising to modernize transportation systems and create thousands of jobs.",
        "sources": [
          "Associated Press",
          "NPR",
          "Reuters"
        ]
      },
      {
        "headline": "New Legislation Aims to Reform Healthcare System",
        "text": "A diplomatic breakthrough has been achieved in international relations, easing tensions between major world powers.",
        "sources": [
          "The Wall Street Journal"
        ]
      }
    ]
  },
  "gaming": {
    "emoji": "\ud83c\udfae",
    "headlines": [
      {
        "headline": "Indie Game Developer Secures Major Publishing Deal",
        "text": "A leading game studio has announced an exclusive title for next-generation consoles, featuring groundbreaking graphics and innovative gameplay mechanics.",
        "sources": [
          "Reuters"
        ]
      },
      {
        "headline": "Major Game Studio Announces Next-Gen Console Exclusive",
        "text": "An independent game developer has secured a major publishing deal that will bring their unique vision to a global audience.",
        "sources": [
          "Bloomberg",
          "The New York Times"
        ]
      },
      {
        "headline": "Gaming Platform Announces Cross-Platform Play Support",
        "text": "An independent game developer has secured a major publishing deal that will bring their unique vision to a global audience.",
        "sources": [
          "Associated Press",
          "CNN",
          "The Wall Street Journal"
        ]
      }
    ]
  }
}